setup.cfg
setup.py
projkit/__init__.py
projkit/commands.py
test/test_commands.py
umich_projkit.egg-info/PKG-INFO
umich_projkit.egg-info/SOURCES.txt
umich_projkit.egg-info/dependency_links.txt
umich_projkit.egg-info/entry_points.txt
umich_projkit.egg-info/requires.txt
umich_projkit.egg-info/top_level.txt