Metadata-Version: 1.0
Name: umich-projkit
Version: 2.0.2
Summary: Automatically grade projects for your CS course. Written for University of Michigan's EECS 281 -- Data Structures and Algorithms.
Home-page: https://gitlab.eecs.umich.edu/eecs281/projkit
Author: Waleed Khan
Author-email: wkhan@umich.edu
License: UNKNOWN
Platform: UNKNOWN
